{
  "id": "pendant-bridge",
  "title": "Pendant Bridge",
  "description": "Relays Foundry actors, inventory, chat, and dice rolls to a pendant-home (COA) module over a local WebSocket. Adds the Anti-Hammer Space inventory (body paperdoll + hex storage + rules engine) to actor sheets.",
  "version": "0.30.0",
  "compatibility": {
    "minimum": "11",
    "verified": "14"
  },
  "authors": [
    { "name": "Pendant", "url": "" }
  ],
  "esmodules": ["scripts/main.js"],
  "styles": ["styles/pendant-bridge.css"],
  "languages": [
    { "lang": "en", "name": "English", "path": "lang/en.json" }
  ],
  "url": "https://github.com/NGZNinjaKing18/foundry-pendant-bridge",
  "manifest": "https://github.com/NGZNinjaKing18/foundry-pendant-bridge/releases/latest/download/module.json",
  "download": "https://github.com/NGZNinjaKing18/foundry-pendant-bridge/releases/latest/download/foundry-pendant-bridge.zip",
  "license": "",
  "readme": "",
  "bugs": "",
  "changelog": "",
  "flags": {}
}
